{"type":"footer","name":"Footer","sections":{"be8b2d35-417a-4dbe-b6fb-2474f15fbd93":{"type":"image--image-with-text","settings":{"image":"shopify:\/\/shop_images\/IMG_2644.jpg","text_overlapping_image":false,"section-width":"full","layout":"left","text_alignment":"center","title":"Hier findest du die besten Rezepte für deinen Alltag","text":"<p><strong>LASS DICH INSPIRIEREN…<\/strong><\/p><p>…von unseren <a href=\"\/pages\/rezepte\" target=\"_blank\" title=\"Rezepte\">Rezepten<\/a>, die wir für dich kreiert haben. In vielen unserer Rezepte verwenden wir Yacon Sirup anstatt herkömmlichen Sirup oder Zucker. Wir bei Vitabel Nutrition sind immer auf der Suche nach den neuesten und leckersten Kreationen in der Küche und freuen uns, wenn du unsere Rezepte ausprobierst und verwendest. Auf unserem Instagram-Kanal findest du noch mehr tolle & schmackhafte Alternativen, die dich und deine Familie, sowie Freunde begeistern werden. <\/p><p>Du hast Anregungen oder ein neues kreatives Rezept, das wir unbedingt probieren sollen? <\/p><p>Schreibe uns und wir teilen es gerne mit der Community in deinem Namen und verlinken dich, wenn du das wünschst! <\/p><p><br\/><\/p>","button_label":"","button_link":"","colors":"accent"}},"footer-main":{"type":"footer-main","blocks":{"menu":{"type":"menu","settings":{"menu_title":"Quick links","footer_linklist":"footer"}},"social":{"type":"social","settings":{"social_title":"Get connected via Instagram"}},"text":{"type":"text","settings":{"title":"Healthy meets Tasty","richtext":"<p>Auserwählte Zutaten. Gesüßt mit dem Besten aus der Yacon Wurzel, die auch für Diabetiker geeignet ist.<\/p><p>Für Dich und dein Wohlbefinden.<\/p><p><em>100% vegan. 100% frei von Gluten. 100% Bio. Du wirst es lieben!<\/em><\/p><p><br\/><\/p>"}},"newsletter":{"type":"newsletter","settings":{"newsletter_title":"Newsletter","footer_newsletter_description":""}}},"block_order":["menu","social","text","newsletter"],"settings":{"alignment":"left"}},"footer-bottom":{"type":"footer-bottom","settings":{"show_methods_of_payment":true,"center_content_on_desktop":false,"footer_text":"","show_currency_selector":true,"show_locale_selector":false}}},"order":["be8b2d35-417a-4dbe-b6fb-2474f15fbd93","footer-main","footer-bottom"]}